LICENSE
example.yaml
traffictoll/__init__.py
traffictoll/__main__.py
traffictoll/cli.py
traffictoll/exceptions.py
traffictoll/net.py
traffictoll/speedtest.py
traffictoll/tc.py
traffictoll/utils.py
traffictoll-1.5.0.dist-info/entry_points.txt
traffictoll-1.5.0.dist-info/LICENSE
traffictoll-1.5.0.dist-info/WHEEL
traffictoll-1.5.0.dist-info/METADATA
traffictoll-1.5.0.dist-info/RECORD
