Metadata-Version: 2.1
Name: traffictoll
Version: 1.5.0
Summary: NetLimiter-like bandwidth limiting and QoS for Linux
Home-page: https://github.com/cryzed/TrafficToll
Keywords: traffic,traffic control,traffic shaping,tc,netlimiter,qos
Author: Chris Braun
Author-email: cryzed@googlemail.com
Requires-Python: >=3.6,<4.0
Classifier: Programming Language :: Python :: 3
Classifier: Programming Language :: Python :: 3.6
Classifier: Programming Language :: Python :: 3.7
Classifier: Programming Language :: Python :: 3.8
Requires-Dist: loguru (>=0.4.1,<0.5.0)
Requires-Dist: psutil (>=5.6.7,<6.0.0)
Requires-Dist: ruamel.yamL (>=0.16.6,<0.17.0)
Project-URL: Repository, https://github.com/cryzed/TrafficToll
